primus_lens_training_toolkit/__init__.py
primus_lens_training_toolkit/sitecustomize.py
primus_lens_training_toolkit/wandb_wrapper/__init__.py
primus_lens_training_toolkit/wandb_wrapper/run.py
primus_lens_training_toolkit-0.1.1.dist-info/METADATA
primus_lens_training_toolkit-0.1.1.dist-info/WHEEL
primus_lens_training_toolkit-0.1.1.dist-info/top_level.txt
primus_lens_training_toolkit-0.1.1.dist-info/RECORD
