Metadata-Version: 2.4
Name: primus-lens-training-toolkit
Version: 0.1.1
Summary: Add your description here
Requires-Python: >=3.10
Requires-Dist: wandb>=0.21.4
